recorder_utils/__init__.py
recorder_utils/build_offset_intervals.py
recorder_utils/creader_wrapper.py
recorder_utils/exclusions.py
recorder_utils/libreader.cpython-310-x86_64-linux-gnu.so
recorder_utils/lookup3.py
recorder_utils/mpi_constants.py
recorder_utils/mpiio_handler.py
recorder_utils/posix_handler.py
recorder_utils/reader.h
recorder_utils/recorder-logger.h
recorder_utils/recorder2csv.py
recorder_utils/uthash.h
recorder_utils-0.5.0.dist-info/LICENSE
recorder_utils-0.5.0.dist-info/METADATA
recorder_utils-0.5.0.dist-info/WHEEL
recorder_utils-0.5.0.dist-info/entry_points.txt
recorder_utils-0.5.0.dist-info/top_level.txt
recorder_utils-0.5.0.dist-info/RECORD
